blockpipe_db/__init__.py
blockpipe_db/client.py
blockpipe_db/msg.py
blockpipe_db-0.1.9.dist-info/METADATA
blockpipe_db-0.1.9.dist-info/WHEEL
blockpipe_db-0.1.9.dist-info/RECORD
