Metadata-Version: 2.1
Name: blockpipe-db
Version: 0.1.9
Summary: 
Author: Sorawit Suriyakarn
Author-email: thepsint@gmail.com
Requires-Python: >=3.6,<4.0
Classifier: Programming Language :: Python :: 3
Classifier: Programming Language :: Python :: 3.6
Classifier: Programming Language :: Python :: 3.7
Classifier: Programming Language :: Python :: 3.8
Classifier: Programming Language :: Python :: 3.9
Classifier: Programming Language :: Python :: 3.10
Classifier: Programming Language :: Python :: 3.11
Requires-Dist: hexbytes (>=0.3.0,<0.4.0)
Requires-Dist: msgpack (>=1.0.5,<2.0.0)
Requires-Dist: pandas (>=2.0.1,<3.0.0)
Requires-Dist: pyzmq (>=25.1.0,<26.0.0)
